Metadata-Version: 2.1
Name: cmd.pyo
Version: 1.0
Summary: My CMD 模組
Home-page: UNKNOWN
License: LGPL
Platform: UNKNOWN
